CHANGELOG.md
LICENSE
MANIFEST.in
README.md
setup.py
textlines/__init__.py
textlines/__main__.py
textlines/cli.py
textlines/emoji.py
textlines/humanize_time.py
textlines.egg-info/PKG-INFO
textlines.egg-info/SOURCES.txt
textlines.egg-info/dependency_links.txt
textlines.egg-info/entry_points.txt
textlines.egg-info/requires.txt
textlines.egg-info/top_level.txt