Metadata-Version: 1.0
Name: textlines
Version: 0.0.1
Summary: ("\nSparklines for text. text_lines counts your words, paragraphs, pages\nand emits a short summary.\n\nThe text doesn't need to be here, but I'm trying to write a new paragraph.\n", '\n')
Home-page: https://github.com/michaeljoseph/textlines
Author: Michael Joseph
Author-email: michaeljoseph@gmail.com
License: Apache License
